{"version": "5.8.3", "flags": {}, "shapes": [{"label": "bitou_bush", "points": [[436.1505376344086, 499.63440860215053], [528.6236559139785, 599.6344086021505]], "group_id": null, "description": "", "shape_type": "rectangle", "flags": {}, "mask": null}, {"label": "bitou_bush", "points": [[510.3440860215054, 469.52688172043014], [614.6451612903226, 575.9784946236559]], "group_id": null, "description": "", "shape_type": "rectangle", "flags": {}, "mask": null}, {"label": "bitou_bush", "points": [[464.10752688172045, 370.60215053763443], [565.1827956989247, 460.9247311827957]], "group_id": null, "description": "", "shape_type": "rectangle", "flags": {}, "mask": null}, {"label": "bitou_bush", "points": [[582.3870967741935, 397.48387096774195], [682.3870967741935, 458.77419354838713]], "group_id": null, "description": "", "shape_type": "rectangle", "flags": {}, "mask": null}, {"label": "bitou_bush", "points": [[608.1935483870967, 459.8494623655914], [678.0860215053764, 524.3655913978495]], "group_id": null, "description": "", "shape_type": "rectangle", "flags": {}, "mask": null}, {"label": "bitou_bush", "points": [[340.45161290322585, 366.3010752688172], [404.9677419354839, 405.01075268817203]], "group_id": null, "description": "", "shape_type": "rectangle", "flags": {}, "mask": null}, {"label": "bitou_bush", "points": [[442.60215053763443, 557.6989247311828], [552.2795698924732, 652.3225806451613]], "group_id": null, "description": "", "shape_type": "rectangle", "flags": {}, "mask": null}, {"label": "bitou_bush", "points": [[521.0967741935484, 153.39784946236563], [600.6666666666666, 199.63440860215056]], "group_id": null, "description": "", "shape_type": "rectangle", "flags": {}, "mask": null}], "imagePath": "bitou_bush_56.jpeg", "imageData": null, "imageHeight": 1024, "imageWidth": 768}