{
  "version": "5.8.3",
  "flags": {},
  "shapes": [
    {
      "label": "halogeton_leaves",
      "points": [
        [
          332.90163934426226,
          197.93442622950823
        ],
        [
          774.7049180327868,
          534.8196721311475
        ]
      ],
      "group_id": null,
      "description": "",
      "shape_type": "rectangle",
      "flags": {},
      "mask": null
    },
    {
      "label": "halogeton_leaves",
      "points": [
        [
          82.90163934426229,
          162.68852459016395
        ],
        [
          226.34426229508196,
          268.42622950819674
        ]
      ],
      "group_id": null,
      "description": "",
      "shape_type": "rectangle",
      "flags": {},
      "mask": null
    }
  ],
  "imagePath": "halogeton_leaves_21.jpg",
  "imageData": null,
  "imageHeight": 768,
  "imageWidth": 1024
}