{"version": "5.8.3", "flags": {}, "shapes": [{"label": "lantana", "points": [[128.7674418604651, 256.7674418604651], [333.4186046511628, 431.1860465116279]], "group_id": null, "description": "", "shape_type": "rectangle", "flags": {}, "mask": null}, {"label": "lantana", "points": [[119.46511627906978, 678.8604651162791], [267.13953488372096, 895.1395348837209]], "group_id": null, "description": "", "shape_type": "rectangle", "flags": {}, "mask": null}], "imagePath": "lantana_74.jpg", "imageData": null, "imageHeight": 1024, "imageWidth": 768}