{"version": "5.8.3", "flags": {}, "shapes": [{"label": "mouse_ear_hawkweed", "points": [[415.3018867924528, 113.16981132075475], [527.566037735849, 200.90566037735854]], "group_id": null, "description": "", "shape_type": "rectangle", "flags": {}, "mask": null}, {"label": "mouse_ear_hawkweed", "points": [[523.7924528301887, 282.9811320754717], [639.8301886792452, 362.2264150943396]], "group_id": null, "description": "", "shape_type": "rectangle", "flags": {}, "mask": null}], "imagePath": "mouse_ear_hawkweed_92.jpg", "imageData": null, "imageHeight": 782, "imageWidth": 1024}