{
  "version": "5.8.3",
  "flags": {},
  "shapes": [
    {
      "label": "portuguese_bloom_seed",
      "points": [
        [
          205.42857142857147,
          310.0952380952381
        ],
        [
          508.28571428571433,
          655.8095238095239
        ]
      ],
      "group_id": null,
      "description": "",
      "shape_type": "rectangle",
      "flags": {},
      "mask": null
    },
    {
      "label": "portuguese_bloom_seed",
      "points": [
        [
          174.952380952381,
          719.6190476190476
        ],
        [
          406.3809523809524,
          974.8571428571429
        ]
      ],
      "group_id": null,
      "description": "",
      "shape_type": "rectangle",
      "flags": {},
      "mask": null
    }
  ],
  "imagePath": "portuguese_bloom_seed_83.jpeg",
  "imageData": null,
  "imageHeight": 1024,
  "imageWidth": 768
}